circuitpython_mocks/__init__.py
circuitpython_mocks/_mixins.py
circuitpython_mocks/board.py
circuitpython_mocks/fixtures.py
circuitpython_mocks/busio/__init__.py
circuitpython_mocks/busio/operations.py
circuitpython_mocks/digitalio/__init__.py
circuitpython_mocks/digitalio/operations.py
circuitpython_mocks-0.3.1.dist-info/LICENSE
circuitpython_mocks-0.3.1.dist-info/METADATA
circuitpython_mocks-0.3.1.dist-info/WHEEL
circuitpython_mocks-0.3.1.dist-info/top_level.txt
circuitpython_mocks-0.3.1.dist-info/RECORD
